endi_payment/__init__.py
endi_payment/archive.py
endi_payment/database.py
endi_payment/history.py
endi_payment/interfaces.py
endi_payment/models.py
endi_payment/public.py
endi_payment/scripts.py
endi_payment/alembic/__init__.py
endi_payment/alembic/env.py
endi_payment/alembic/script.py.mako
endi_payment/alembic/versions/5_1_2_initial_state_aaaaaaaaaaaa.py
endi_payment/alembic/versions/5_1_4_update_endi_payment_afcf321a324d.py
endi_payment/alembic/versions/__init__.py
endi_payment/views/__init__.py
endi_payment/views/archive.py
endi_payment/views/forms.py
endi_payment/views/history.py
endi_payment/views/routes.py
endi_payment/views/templates/histories.mako
endi_payment/views/templates/history.mako
endi_payment/views/templates/local_archive_list_item_panel.mako
endi_payment/views/templates/local_archive_panel.mako
endi_payment-2.5.1.dist-info/LICENSE.txt
endi_payment-2.5.1.dist-info/METADATA
endi_payment-2.5.1.dist-info/WHEEL
endi_payment-2.5.1.dist-info/entry_points.txt
endi_payment-2.5.1.dist-info/top_level.txt
endi_payment-2.5.1.dist-info/RECORD
