Metadata-Version: 2.1
Name: endi-payment
Version: 2.5.1
Summary: endi_payment
Home-page: https://framagit.org/endi/endi_payment
Author: Majerti
Author-email: equipe@majerti.fr
License: GPLv3
Keywords: web wsgi bfg pylons pyramid endi
Classifier: License :: OSI Approved :: GNU General Public License v3 (GPLv3)
Classifier: Programming Language :: Python
Classifier: Framework :: Pyramid
Classifier: Topic :: Internet :: WWW/HTTP
Classifier: Topic :: Internet :: WWW/HTTP :: WSGI :: Application
License-File: LICENSE.txt
Provides-Extra: testing
Requires-Dist: WebTest (>=1.3.1) ; extra == 'testing'
Requires-Dist: pytest ; extra == 'testing'
Requires-Dist: pytest-cov ; extra == 'testing'
